[
  {
    "device": "desktop",
    "slug": "rd-calculator",
    "scope": "sticky",
    "summary": {
      "headings": "PASS",
      "images": "PASS",
      "buttons": "FAIL",
      "links": "FAIL",
      "canonical": "PASS",
      "meta": "PASS",
      "og_tags": "PASS",
      "sticky": "FAIL"
    },
    "details": {
      "headings": [],
      "images": [],
      "buttons": [
        {
          "type": "button_count",
          "ref_count": 10,
          "live_count": 5,
          "message": "Button count (identifiable): expected 10, found 5"
        },
        {
          "type": "missing_button",
          "bbox": {
            "x": 792.390625,
            "y": 32.5,
            "width": 20,
            "height": 20
          },
          "message": "Missing button: '' (href: '')"
        },
        {
          "type": "missing_button",
          "bbox": {
            "x": 1238,
            "y": 30.5,
            "width": 24,
            "height": 24
          },
          "message": "Missing button: '' (href: '')"
        },
        {
          "type": "missing_button",
          "bbox": {
            "x": 559.4296875,
            "y": 32.5,
            "width": 17.4765625,
            "height": 20
          },
          "message": "Missing button: '' (href: '')"
        },
        {
          "type": "missing_button",
          "bbox": {
            "x": 408.0625,
            "y": 32.5,
            "width": 17.4765625,
            "height": 20
          },
          "message": "Missing button: '' (href: '')"
        },
        {
          "type": "missing_button",
          "bbox": {
            "x": 665.0078125,
            "y": 32.5,
            "width": 17.4140625,
            "height": 20
          },
          "message": "Missing button: '' (href: '')"
        },
        {
          "type": "missing_button",
          "bbox": {
            "x": 252.9453125,
            "y": 32.5,
            "width": 17.46875,
            "height": 20
          },
          "message": "Missing button: '' (href: '')"
        },
        {
          "type": "missing_button",
          "bbox": {
            "x": 1001.359375,
            "y": 16,
            "width": 113.9296875,
            "height": 53
          },
          "message": "Missing button: 'Join as Advisor' (href: '')"
        },
        {
          "type": "extra_button",
          "bbox": {
            "x": 1228,
            "y": 20,
            "width": 40,
            "height": 40
          },
          "message": "Extra button in live: '' (href: '')"
        },
        {
          "type": "extra_button",
          "bbox": {
            "x": 905.28125,
            "y": 22,
            "width": 46,
            "height": 36
          },
          "message": "Extra button in live: '' (href: '')"
        },
        {
          "type": "button_label_mismatch",
          "bbox": {
            "x": 1116,
            "y": 21.5,
            "width": 100,
            "height": 37
          },
          "message": "Button label mismatch for 'text:login': expected 'Login', found 'Login'"
        }
      ],
      "links": [
        {
          "type": "link_count",
          "ref_count": 9,
          "live_count": 10,
          "message": "Link count: expected 9, found 10"
        },
        {
          "type": "extra_link",
          "bbox": {
            "x": 963.28125,
            "y": 22.5,
            "width": 140.71875,
            "height": 35
          },
          "message": "Extra link (1x): /join-max-life/become-an-agent"
        }
      ],
      "canonical": [],
      "meta": [],
      "og_tags": [],
      "sticky": [
        {
          "type": "sticky_count",
          "ref_count": 2,
          "live_count": 3,
          "message": "Sticky count differs (ref=2 live=3)"
        }
      ]
    }
  },
  {
    "device": "android",
    "slug": "rd-calculator",
    "scope": "sticky",
    "summary": {
      "headings": "PASS",
      "images": "FAIL",
      "buttons": "FAIL",
      "links": "PASS",
      "canonical": "PASS",
      "meta": "PASS",
      "og_tags": "PASS",
      "sticky": "FAIL"
    },
    "details": {
      "headings": [],
      "images": [
        {
          "type": "alt_mismatch",
          "bbox": {
            "x": 12,
            "y": 10,
            "width": 110,
            "height": 40
          },
          "message": "Alt mismatch. Expected 'Axis Max Life Insurance', found 'Logo of axis max life insurance graphic'"
        }
      ],
      "buttons": [
        {
          "type": "button_count",
          "ref_count": 2,
          "live_count": 3,
          "message": "Button count (identifiable): expected 2, found 3"
        },
        {
          "type": "missing_button",
          "bbox": {
            "x": 357,
            "y": 18,
            "width": 24,
            "height": 24
          },
          "message": "Missing button: '' (href: '')"
        },
        {
          "type": "extra_button",
          "bbox": {
            "x": 341,
            "y": 10,
            "width": 40,
            "height": 40
          },
          "message": "Extra button in live: '' (href: '')"
        },
        {
          "type": "extra_button",
          "bbox": {
            "x": 12,
            "y": 68,
            "width": 369,
            "height": 26
          },
          "message": "Extra button in live: 'RD Calculator' (href: '')"
        }
      ],
      "links": [],
      "canonical": [],
      "meta": [],
      "og_tags": [],
      "sticky": [
        {
          "type": "sticky_count",
          "ref_count": 2,
          "live_count": 3,
          "message": "Sticky count differs (ref=2 live=3)"
        }
      ]
    }
  },
  {
    "device": "ios",
    "slug": "rd-calculator",
    "scope": "sticky",
    "summary": {
      "headings": "PASS",
      "images": "FAIL",
      "buttons": "FAIL",
      "links": "PASS",
      "canonical": "PASS",
      "meta": "PASS",
      "og_tags": "PASS",
      "sticky": "FAIL"
    },
    "details": {
      "headings": [],
      "images": [
        {
          "type": "alt_mismatch",
          "bbox": {
            "x": 12,
            "y": 10,
            "width": 110,
            "height": 40
          },
          "message": "Alt mismatch. Expected 'Axis Max Life Insurance', found 'Logo of axis max life insurance graphic'"
        }
      ],
      "buttons": [
        {
          "type": "button_count",
          "ref_count": 2,
          "live_count": 3,
          "message": "Button count (identifiable): expected 2, found 3"
        },
        {
          "type": "missing_button",
          "bbox": {
            "x": 339,
            "y": 18,
            "width": 24,
            "height": 24
          },
          "message": "Missing button: '' (href: '')"
        },
        {
          "type": "extra_button",
          "bbox": {
            "x": 323,
            "y": 10,
            "width": 40,
            "height": 40
          },
          "message": "Extra button in live: '' (href: '')"
        },
        {
          "type": "extra_button",
          "bbox": {
            "x": 12,
            "y": 68,
            "width": 351,
            "height": 26
          },
          "message": "Extra button in live: 'RD Calculator' (href: '')"
        }
      ],
      "links": [],
      "canonical": [],
      "meta": [],
      "og_tags": [],
      "sticky": [
        {
          "type": "sticky_count",
          "ref_count": 2,
          "live_count": 3,
          "message": "Sticky count differs (ref=2 live=3)"
        }
      ]
    }
  }
]